[[1.391527,{"lines":{"0":[["                                                                                                                                                             ",{}]],"1":[["               +                ",{"fg":4,"bold":true}],["                                                                                                                             ",{}]],"2":[["               #                ",{"fg":4,"bold":true}],["                                                                                                                             ",{}]],"3":[["              ###               ",{"fg":4,"bold":true}],["                                                                                                                             ",{}]],"4":[["             #####              ",{"fg":4,"bold":true}],["                                                                                                                             ",{}]],"5":[["             ######             ",{"fg":4,"bold":true}],["                                                                                                                             ",{}]],"6":[["            ; #####;            User: ",{"fg":4,"bold":true}],["jhonatan                                                                                                               ",{}]],"7":[["           +##.#####            Hostname: ",{"fg":4,"bold":true}],["Arch-linux                                                                                                         ",{}]],"8":[["          +##########           Distro: ",{"fg":4,"bold":true}],["Arch Linux                                                                                                           ",{}]],"9":[["         ######",{"fg":4,"bold":true}],["#####",{"fg":4}],["##;         Kernel: ",{"fg":4,"bold":true}],["3.18.2-2-ARCH                                                                                                        ",{}]],"10":[["                                                                                                                                                             ",{}]],"11":[["                                                                                                                                                             ",{}]],"12":[["                                                                                                                                                             ",{}]],"13":[["                                                                                                                                                             ",{}]],"14":[["                                                                                                                                                             ",{}]],"15":[["                                                                                                                                                             ",{}]],"16":[["                                                                                                                                                             ",{}]],"17":[["                                                                                                                                                             ",{}]],"18":[["                                                                                                                                                             ",{}]],"19":[["                                                                                                                                                             ",{}]],"20":[["                                                                                                                                                             ",{}]],"21":[["                                                                                                                                                             ",{}]],"22":[["                                                                                                                                                             ",{}]],"23":[["                                                                                                                                                             ",{}]],"24":[["                                                                                                                                                             ",{}]],"25":[["                                                                                                                                                             ",{}]],"26":[["                                                                                                                                                             ",{}]],"27":[["                                                                                                                                                             ",{}]],"28":[["                                                                                                                                                             ",{}]],"29":[["                                                                                                                                                             ",{}]],"30":[["                                                                                                                                                             ",{}]],"31":[["                                                                                                                                                             ",{}]],"32":[["                                                                                                                                                             ",{}]],"33":[["                                                                                                                                                             ",{}]],"34":[["                                                                                                                                                             ",{}]],"35":[["                                                                                                                                                             ",{}]],"36":[["                                                                                                                                                             ",{}]],"37":[["                                                                                                                                                             ",{}]],"38":[["                                                                                                                                                             ",{}]],"39":[["                                                                                                                                                             ",{}]],"40":[["                                                                                                                                                             ",{}]],"41":[["                                                                                                                                                             ",{}]],"42":[["                                                                                                                                                             ",{}]],"43":[["                                                                                                                                                             ",{}]],"44":[["                                                                                                                                                             ",{}]]},"cursor":{"x":0,"y":10,"visible":true}}],[0.000368,{"lines":{"10":[["        ###",{"fg":4,"bold":true}],["############",{"fg":4}],["+        Uptime: ",{"fg":4,"bold":true}],["3:06                                                                                                                 ",{}]],"11":[["       #",{"fg":4,"bold":true}],["######   #######        ",{"fg":4}],["Window Manager: ",{"fg":4,"bold":true}],["KWin                                                                                                         ",{}]],"12":[["     .######;     ;###;`\".      ",{"fg":4}],["Desktop Environment: ",{"fg":4,"bold":true}],["KDE                                                                                                     ",{}]],"13":[["    .#######;     ;#####.       ",{"fg":4}],["Shell: ",{"fg":4,"bold":true}],["/bin/bash                                                                                                             ",{}]],"14":[["    #########.   .########`     ",{"fg":4}],["Terminal: ",{"fg":4,"bold":true}],["xterm                                                                                                              ",{}]],"15":[["   ######'           '######    ",{"fg":4}],["Packages: ",{"fg":4,"bold":true}],["957                                                                                                                ",{}]],"16":[["  ;####                 ####;   ",{"fg":4}],["CPU: ",{"fg":4,"bold":true}],["AMD Athlon(tm) II X2 215 Processor                                                                                      ",{}]],"17":[["  ##'                     '##   ",{"fg":4}],["RAM: ",{"fg":4,"bold":true}],["823 MB ",{"fg":3}],["/ 1753 MB                                                                                                        ",{}]],"18":[[" #'                         `#  ",{"fg":4}],["Disk: ",{"fg":4,"bold":true}],["14G ",{"fg":2}],["/ 292G                                                                                                             ",{}]]},"cursor":{"y":20}}],[0.045089,{}],[0.046773,{"lines":{"20":[["[jhonatan@Arch-linux ~]$                                                                                                                                     ",{}]]},"cursor":{"x":25}}],[37.796916,{"lines":{"20":[["[jhonatan@Arch-linux ~]$ asciinema auth                                                                                                                      ",{}]]},"cursor":{"x":39}}],[0.9491309999999999,{"cursor":{"x":0,"y":21}}],[0.004836999999999999,{"lines":{"21":[["Open the following URL in your browser to register your API token and assign any recorded asciicasts to your profile:                                        ",{}]],"22":[["https://asciinema.org/connect/c5d5efc3-9f46-442f-9f8a-b6db736d8106                                                                                           ",{}]],"23":[["[jhonatan@Arch-linux ~]$                                                                                                                                     ",{}]]},"cursor":{"x":25,"y":23}}],[12.541575,{"lines":{"23":[["[jhonatan@Arch-linux ~]$ https://asciinema.org/connect/c5d5efc3-9f46-442f-9f8a-b6db736d8106                                                                  ",{}]]},"cursor":{"x":0,"y":24}}],[0.000506,{"lines":{"24":[["bash: https://asciinema.org/connect/c5d5efc3-9f46-442f-9f8a-b6db736d8106: No existe el fichero o el directorio                                               ",{}]],"25":[["[jhonatan@Arch-linux ~]$                                                                                                                                     ",{}]]},"cursor":{"x":25,"y":25}}],[64.088943,{"lines":{"25":[["[jhonatan@Arch-linux ~]$ exit                                                                                                                                ",{}]]},"cursor":{"x":0,"y":26}}]]