[[0.042274,{"lines":{"0":[["patrice@lair",{"fg":2,"bold":true}],[" ~ $",{"fg":4,"bold":true}],["                                                                                                                           ",{}]],"1":[["                                                                                                                                           ",{}]],"2":[["                                                                                                                                           ",{}]],"3":[["                                                                                                                                           ",{}]],"4":[["                                                                                                                                           ",{}]],"5":[["                                                                                                                                           ",{}]],"6":[["                                                                                                                                           ",{}]],"7":[["                                                                                                                                           ",{}]],"8":[["                                                                                                                                           ",{}]],"9":[["                                                                                                                                           ",{}]],"10":[["                                                                                                                                           ",{}]],"11":[["                                                                                                                                           ",{}]],"12":[["                                                                                                                                           ",{}]],"13":[["                                                                                                                                           ",{}]],"14":[["                                                                                                                                           ",{}]],"15":[["                                                                                                                                           ",{}]],"16":[["                                                                                                                                           ",{}]],"17":[["                                                                                                                                           ",{}]],"18":[["                                                                                                                                           ",{}]],"19":[["                                                                                                                                           ",{}]],"20":[["                                                                                                                                           ",{}]],"21":[["                                                                                                                                           ",{}]],"22":[["                                                                                                                                           ",{}]],"23":[["                                                                                                                                           ",{}]],"24":[["                                                                                                                                           ",{}]],"25":[["                                                                                                                                           ",{}]],"26":[["                                                                                                                                           ",{}]],"27":[["                                                                                                                                           ",{}]],"28":[["                                                                                                                                           ",{}]],"29":[["                                                                                                                                           ",{}]],"30":[["                                                                                                                                           ",{}]],"31":[["                                                                                                                                           ",{}]],"32":[["                                                                                                                                           ",{}]],"33":[["                                                                                                                                           ",{}]],"34":[["                                                                                                                                           ",{}]],"35":[["                                                                                                                                           ",{}]],"36":[["                                                                                                                                           ",{}]],"37":[["                                                                                                                                           ",{}]],"38":[["                                                                                                                                           ",{}]],"39":[["                                                                                                                                           ",{}]],"40":[["                                                                                                                                           ",{}]],"41":[["                                                                                                                                           ",{}]],"42":[["                                                                                                                                           ",{}]],"43":[["                                                                                                                                           ",{}]],"44":[["                                                                                                                                           ",{}]],"45":[["                                                                                                                                           ",{}]],"46":[["                                                                                                                                           ",{}]]},"cursor":{"x":17,"y":0,"visible":true}}],[4.993382,{"lines":{"0":[["patrice@lair",{"fg":2,"bold":true}],[" ~ $",{"fg":4,"bold":true}],[" h                                                                                                                         ",{}]]},"cursor":{"x":18}}],[0.119357,{"lines":{"0":[["patrice@lair",{"fg":2,"bold":true}],[" ~ $",{"fg":4,"bold":true}],[" he                                                                                                                        ",{}]]},"cursor":{"x":19}}],[0.112841,{"lines":{"0":[["patrice@lair",{"fg":2,"bold":true}],[" ~ $",{"fg":4,"bold":true}],[" hel                                                                                                                       ",{}]]},"cursor":{"x":20}}],[0.126803,{"lines":{"0":[["patrice@lair",{"fg":2,"bold":true}],[" ~ $",{"fg":4,"bold":true}],[" hell                                                                                                                      ",{}]]},"cursor":{"x":21}}],[0.185557,{"lines":{"0":[["patrice@lair",{"fg":2,"bold":true}],[" ~ $",{"fg":4,"bold":true}],[" hello                                                                                                                     ",{}]]},"cursor":{"x":22}}],[0.159439,{"cursor":{"x":23}}],[0.126784,{"lines":{"0":[["patrice@lair",{"fg":2,"bold":true}],[" ~ $",{"fg":4,"bold":true}],[" hello w                                                                                                                   ",{}]]},"cursor":{"x":24}}],[0.071532,{"lines":{"0":[["patrice@lair",{"fg":2,"bold":true}],[" ~ $",{"fg":4,"bold":true}],[" hello wo                                                                                                                  ",{}]]},"cursor":{"x":25}}],[0.099674,{"lines":{"0":[["patrice@lair",{"fg":2,"bold":true}],[" ~ $",{"fg":4,"bold":true}],[" hello wor                                                                                                                 ",{}]]},"cursor":{"x":26}}],[0.493918,{"lines":{"0":[["patrice@lair",{"fg":2,"bold":true}],[" ~ $",{"fg":4,"bold":true}],[" hello worl                                                                                                                ",{}]]},"cursor":{"x":27}}],[0.10286,{"lines":{"0":[["patrice@lair",{"fg":2,"bold":true}],[" ~ $",{"fg":4,"bold":true}],[" hello world                                                                                                               ",{}]]},"cursor":{"x":28}}],[0.176461,{"cursor":{"x":29}}],[0.136487,{"lines":{"0":[["patrice@lair",{"fg":2,"bold":true}],[" ~ $",{"fg":4,"bold":true}],[" hello world :                                                                                                             ",{}]]},"cursor":{"x":30}}],[0.199714,{"lines":{"0":[["patrice@lair",{"fg":2,"bold":true}],[" ~ $",{"fg":4,"bold":true}],[" hello world :)                                                                                                            ",{}]]},"cursor":{"x":31}}],[0.119975,{"cursor":{"x":32}}],[0.12717,{"lines":{"0":[["patrice@lair",{"fg":2,"bold":true}],[" ~ $",{"fg":4,"bold":true}],[" hello world :) !                                                                                                          ",{}]]},"cursor":{"x":33}}],[0.184486,{"cursor":{"x":34}}],[0.768091,{"lines":{"0":[["patrice@lair",{"fg":2,"bold":true}],[" ~ $",{"fg":4,"bold":true}],[" hello world :)                                                                                                            ",{}]]},"cursor":{"x":32}}],[0.168621,{"lines":{"0":[["patrice@lair",{"fg":2,"bold":true}],[" ~ $",{"fg":4,"bold":true}],[" hello world                                                                                                               ",{}]]},"cursor":{"x":29}}],[0.367305,{"lines":{"0":[["patrice@lair",{"fg":2,"bold":true}],[" ~ $",{"fg":4,"bold":true}],[" hello                                                                                                                     ",{}]]},"cursor":{"x":23}}],[1.61072,{"cursor":{"x":17}}],[1.03673,{"lines":{"0":[["patrice@lair",{"fg":2,"bold":true}],[" ~ $",{"fg":4,"bold":true}],[" thello                                                                                                                    ",{}]]},"cursor":{"x":18}}],[0.064833,{"lines":{"0":[["patrice@lair",{"fg":2,"bold":true}],[" ~ $",{"fg":4,"bold":true}],[" thhello                                                                                                                   ",{}]]},"cursor":{"x":19}}],[0.062237,{"lines":{"0":[["patrice@lair",{"fg":2,"bold":true}],[" ~ $",{"fg":4,"bold":true}],[" thihello                                                                                                                  ",{}]]},"cursor":{"x":20}}],[0.10446,{"lines":{"0":[["patrice@lair",{"fg":2,"bold":true}],[" ~ $",{"fg":4,"bold":true}],[" thishello                                                                                                                 ",{}]]},"cursor":{"x":21}}],[0.095509,{"lines":{"0":[["patrice@lair",{"fg":2,"bold":true}],[" ~ $",{"fg":4,"bold":true}],[" this hello                                                                                                                ",{}]]},"cursor":{"x":22}}],[0.09690600000000001,{"lines":{"0":[["patrice@lair",{"fg":2,"bold":true}],[" ~ $",{"fg":4,"bold":true}],[" this ihello                                                                                                               ",{}]]},"cursor":{"x":23}}],[0.055573,{"lines":{"0":[["patrice@lair",{"fg":2,"bold":true}],[" ~ $",{"fg":4,"bold":true}],[" this ishello                                                                                                              ",{}]]},"cursor":{"x":24}}],[0.114958,{"lines":{"0":[["patrice@lair",{"fg":2,"bold":true}],[" ~ $",{"fg":4,"bold":true}],[" this is hello                                                                                                             ",{}]]},"cursor":{"x":25}}],[0.453072,{"lines":{"0":[["patrice@lair",{"fg":2,"bold":true}],[" ~ $",{"fg":4,"bold":true}],[" this is hhello                                                                                                            ",{}]]},"cursor":{"x":26}}],[0.088107,{"lines":{"0":[["patrice@lair",{"fg":2,"bold":true}],[" ~ $",{"fg":4,"bold":true}],[" this is hohello                                                                                                           ",{}]]},"cursor":{"x":27}}],[0.048398,{"lines":{"0":[["patrice@lair",{"fg":2,"bold":true}],[" ~ $",{"fg":4,"bold":true}],[" this is howhello                                                                                                          ",{}]]},"cursor":{"x":28}}],[0.094946,{"lines":{"0":[["patrice@lair",{"fg":2,"bold":true}],[" ~ $",{"fg":4,"bold":true}],[" this is how hello                                                                                                         ",{}]]},"cursor":{"x":29}}],[0.145538,{"lines":{"0":[["patrice@lair",{"fg":2,"bold":true}],[" ~ $",{"fg":4,"bold":true}],[" this is how yhello                                                                                                        ",{}]]},"cursor":{"x":30}}],[0.055254,{"lines":{"0":[["patrice@lair",{"fg":2,"bold":true}],[" ~ $",{"fg":4,"bold":true}],[" this is how yohello                                                                                                       ",{}]]},"cursor":{"x":31}}],[0.08035100000000001,{"lines":{"0":[["patrice@lair",{"fg":2,"bold":true}],[" ~ $",{"fg":4,"bold":true}],[" this is how youhello                                                                                                      ",{}]]},"cursor":{"x":32}}],[0.065516,{"lines":{"0":[["patrice@lair",{"fg":2,"bold":true}],[" ~ $",{"fg":4,"bold":true}],[" this is how you hello                                                                                                     ",{}]]},"cursor":{"x":33}}],[0.430293,{"lines":{"0":[["patrice@lair",{"fg":2,"bold":true}],[" ~ $",{"fg":4,"bold":true}],[" this is how you shello                                                                                                    ",{}]]},"cursor":{"x":34}}],[0.088824,{"lines":{"0":[["patrice@lair",{"fg":2,"bold":true}],[" ~ $",{"fg":4,"bold":true}],[" this is how you shhello                                                                                                   ",{}]]},"cursor":{"x":35}}],[0.09435499999999999,{"lines":{"0":[["patrice@lair",{"fg":2,"bold":true}],[" ~ $",{"fg":4,"bold":true}],[" this is how you shohello                                                                                                  ",{}]]},"cursor":{"x":36}}],[0.097483,{"lines":{"0":[["patrice@lair",{"fg":2,"bold":true}],[" ~ $",{"fg":4,"bold":true}],[" this is how you shouhello                                                                                                 ",{}]]},"cursor":{"x":37}}],[0.159749,{"lines":{"0":[["patrice@lair",{"fg":2,"bold":true}],[" ~ $",{"fg":4,"bold":true}],[" this is how you shoulhello                                                                                                ",{}]]},"cursor":{"x":38}}],[0.054674,{"lines":{"0":[["patrice@lair",{"fg":2,"bold":true}],[" ~ $",{"fg":4,"bold":true}],[" this is how you shouldhello                                                                                               ",{}]]},"cursor":{"x":39}}],[0.105453,{"lines":{"0":[["patrice@lair",{"fg":2,"bold":true}],[" ~ $",{"fg":4,"bold":true}],[" this is how you should hello                                                                                              ",{}]]},"cursor":{"x":40}}],[0.070752,{"lines":{"0":[["patrice@lair",{"fg":2,"bold":true}],[" ~ $",{"fg":4,"bold":true}],[" this is how you should shello                                                                                             ",{}]]},"cursor":{"x":41}}],[0.112154,{"lines":{"0":[["patrice@lair",{"fg":2,"bold":true}],[" ~ $",{"fg":4,"bold":true}],[" this is how you should sahello                                                                                            ",{}]]},"cursor":{"x":42}}],[0.201001,{"lines":{"0":[["patrice@lair",{"fg":2,"bold":true}],[" ~ $",{"fg":4,"bold":true}],[" this is how you should sayhello                                                                                           ",{}]]},"cursor":{"x":43}}],[0.255601,{"lines":{"0":[["patrice@lair",{"fg":2,"bold":true}],[" ~ $",{"fg":4,"bold":true}],[" this is how you should say hello                                                                                          ",{}]]},"cursor":{"x":44}}],[1.024829,{"cursor":{"x":40}}],[0.168018,{"cursor":{"x":33}}],[0.164578,{"cursor":{"x":29}}],[0.050089,{"cursor":{"x":25}}],[0.617094,{"cursor":{"x":0,"y":1}}],[0.095577,{"lines":{"0":[["                                                                                                                                           ",{}]]}}],[0.004428,{"lines":{"46":[["\"/tmp//bash-fc-1060478183\" 1L, 34C                                                                                                         ",{}]]},"cursor":{"x":34,"y":46,"visible":false}}],[0.02962,{"lines":{"0":[["  1 ",{"fg":3,"bold":true}],["this is how you should say hello                                                                                                       ",{"underline":true}]],"1":[["~                                                                                                                                          ",{"fg":4,"bold":true}]],"2":[["~                                                                                                                                          ",{"fg":4,"bold":true}]],"3":[["~                                                                                                                                          ",{"fg":4,"bold":true}]],"4":[["~                                                                                                                                          ",{"fg":4,"bold":true}]],"5":[["~                                                                                                                                          ",{"fg":4,"bold":true}]],"6":[["~                                                                                                                     ",{"fg":4,"bold":true}],["                     ",{}]]},"cursor":{"x":118,"y":6}}],[0.013331,{"lines":{"6":[["~                                                                                                                                          ",{"fg":4,"bold":true}]],"7":[["~                                                                                                                                          ",{"fg":4,"bold":true}]],"8":[["~                                                                                                                                          ",{"fg":4,"bold":true}]],"9":[["~                                                                                                                                          ",{"fg":4,"bold":true}]],"10":[["~                                                                                                                                          ",{"fg":4,"bold":true}]],"11":[["~                                                                                                                                          ",{"fg":4,"bold":true}]],"12":[["~                                                                                                                                          ",{"fg":4,"bold":true}]],"13":[["~                                                                                                                                          ",{"fg":4,"bold":true}]],"14":[["~                                                                                                                                          ",{"fg":4,"bold":true}]],"15":[["~                                                                                                                                          ",{"fg":4,"bold":true}]],"16":[["~                                                                                                                                          ",{"fg":4,"bold":true}]],"17":[["~                                                                                                                                          ",{"fg":4,"bold":true}]],"18":[["~                                                                                                                                          ",{"fg":4,"bold":true}]],"19":[["~                                                                                                                                          ",{"fg":4,"bold":true}]],"20":[["~                                                                                                                                          ",{"fg":4,"bold":true}]],"21":[["~                                                                                                                                          ",{"fg":4,"bold":true}]],"22":[["~                                                                                                                                          ",{"fg":4,"bold":true}]],"23":[["~                                                                                                                                          ",{"fg":4,"bold":true}]],"24":[["~                                                                                                                                          ",{"fg":4,"bold":true}]],"25":[["~                                                                                                                                          ",{"fg":4,"bold":true}]],"26":[["~                                                                                                                                          ",{"fg":4,"bold":true}]],"27":[["~                                                                                                                                          ",{"fg":4,"bold":true}]],"28":[["~                                                                                                                                          ",{"fg":4,"bold":true}]],"29":[["~                                                                                                                                          ",{"fg":4,"bold":true}]],"30":[["~                                                                                                                                          ",{"fg":4,"bold":true}]],"31":[["~                                                                                                                                          ",{"fg":4,"bold":true}]],"32":[["~                                                                                                                                          ",{"fg":4,"bold":true}]],"33":[["~                                                                                                                                          ",{"fg":4,"bold":true}]],"34":[["~                                                                                                                                          ",{"fg":4,"bold":true}]],"35":[["~                                                                                                                                          ",{"fg":4,"bold":true}]],"36":[["~                                                                                                                                          ",{"fg":4,"bold":true}]],"37":[["~                                                                                                                                          ",{"fg":4,"bold":true}]],"38":[["~                                                                                                                                          ",{"fg":4,"bold":true}]],"39":[["~                                                                                                                                          ",{"fg":4,"bold":true}]],"40":[["~                                                                                                                                          ",{"fg":4,"bold":true}]],"41":[["~                                                                                                                                          ",{"fg":4,"bold":true}]],"42":[["~                                                                                                                                          ",{"fg":4,"bold":true}]],"43":[["~                                                                                                                                          ",{"fg":4,"bold":true}]],"44":[["~                                                                                                                                          ",{"fg":4,"bold":true}]],"45":[[" /tmp/bash-fc-1060478183   CWD: /usr/home/patrice   Line: 1                                                                                ",{"fg":3,"bg":4,"bold":true}]]},"cursor":{"x":4,"y":0,"visible":true}}],[0.70616,{"lines":{"46":[["-- INSERT --",{"bold":true}],["                                                                                                                               ",{}]]}}],[0.15083,{"lines":{"0":[["  1 ",{"fg":3,"bold":true}],["ethis is how you should say hello                                                                                                      ",{"underline":true}]],"45":[[" /tmp/bash-fc-1060478183[+]   CWD: /usr/home/patrice   Line: 1                                                                             ",{"fg":3,"bg":4,"bold":true}]]},"cursor":{"x":5}}],[0.112663,{"lines":{"0":[["  1 ",{"fg":3,"bold":true}],["ecthis is how you should say hello                                                                                                     ",{"underline":true}]]},"cursor":{"x":6}}],[0.071259,{"lines":{"0":[["  1 ",{"fg":3,"bold":true}],["echthis is how you should say hello                                                                                                    ",{"underline":true}]]},"cursor":{"x":7}}],[0.041063,{"lines":{"0":[["  1 ",{"fg":3,"bold":true}],["echothis is how you should say hello                                                                                                   ",{"underline":true}]]},"cursor":{"x":8}}],[0.231246,{"lines":{"0":[["  1 ",{"fg":3,"bold":true}],["echo this is how you should say hello                                                                                                  ",{"underline":true}]]},"cursor":{"x":9}}],[0.431459,{"lines":{"0":[["  1 ",{"fg":3,"bold":true}],["echo \"this is how you should say hello                                                                                                 ",{"underline":true}]]},"cursor":{"x":10}}],[0.002914,{"lines":{"0":[["  1 ",{"fg":3,"bold":true}],["echo \"\"this is how you should say hello                                                                                                ",{"underline":true}]]},"cursor":{"x":11}}],[0.045837,{"lines":{"0":[["  1 ",{"fg":3,"bold":true}],["echo \"this is how you should say hello                                                                                                 ",{"underline":true}]]},"cursor":{"x":10}}],[0.615586,{"cursor":{"x":43}}],[0.420582,{"lines":{"0":[["  1 ",{"fg":3,"bold":true}],["echo \"this is how you should say hello \"                                                                                               ",{"underline":true}]]},"cursor":{"x":44}}],[0.002151,{"lines":{"0":[["  1 ",{"fg":3,"bold":true}],["echo \"this is how you should say hello \"\"                                                                                              ",{"underline":true}]]},"cursor":{"x":45}}],[0.032399,{"lines":{"0":[["  1 ",{"fg":3,"bold":true}],["echo \"this is how you should say hello \"                                                                                               ",{"underline":true}]]},"cursor":{"x":44}}],[0.345117,{"lines":{"0":[["  1 ",{"fg":3,"bold":true}],["echo \"this is how you should say hello                                                                                                 ",{"underline":true}]]},"cursor":{"x":43}}],[0.503961,{"cursor":{"x":42}}],[0.735811,{"lines":{"0":[["  1 ",{"fg":3,"bold":true}],["echo \"this is how you should say hello\"                                                                                                ",{"underline":true}]]},"cursor":{"x":43}}],[0.00246,{"lines":{"0":[["  1 ",{"fg":3,"bold":true}],["echo \"this is how you should say hello\"\"                                                                                               ",{"underline":true}]]},"cursor":{"x":44}}],[0.029463,{"lines":{"0":[["  1 ",{"fg":3,"bold":true}],["echo \"this is how you should say hello\"                                                                                                ",{"underline":true}]]},"cursor":{"x":43}}],[0.472953,{"cursor":{"x":44}}],[0.134685,{"lines":{"0":[["  1 ",{"fg":3,"bold":true}],["echo \"this is how you should say hello\" i                                                                                              ",{"underline":true}]]},"cursor":{"x":45}}],[0.087376,{"lines":{"0":[["  1 ",{"fg":3,"bold":true}],["echo \"this is how you should say hello\" in                                                                                             ",{"underline":true}]]},"cursor":{"x":46}}],[0.12153,{"cursor":{"x":47}}],[1.128433,{"lines":{"46":[["                                                                                                                                           ",{}]]},"cursor":{"x":44}}],[0.151553,{"cursor":{"x":42}}],[0.649632,{"cursor":{"x":44}}],[0.340826,{"lines":{"46":[["-- INSERT --",{"bold":true}],["                                                                                                                               ",{}]]}}],[0.099634,{"lines":{"0":[["  1 ",{"fg":3}],["e",{"bg":0}],["cho \"this is how you should say hello\"                                                                                                ",{}]],"1":[["  2 ",{"fg":3,"bold":true}],["in                                                                                                                                     ",{"underline":true}]],"45":[[" /tmp/bash-fc-1060478183[+]   CWD: /usr/home/patrice   Line: 2                                                                             ",{"fg":3,"bg":4,"bold":true}]]},"cursor":{"x":4,"y":1}}],[0.429348,{"lines":{"0":[["  1 ",{"fg":3}],["e",{}],["c",{"bg":0}],["ho \"this is how you should say hello\"                                                                                                ",{}]],"1":[["  2 ",{"fg":3,"bold":true}],["ein                                                                                                                                    ",{"underline":true}]]},"cursor":{"x":5}}],[0.136135,{"lines":{"0":[["  1 ",{"fg":3}],["ec",{}],["h",{"bg":0}],["o \"this is how you should say hello\"                                                                                                ",{}]],"1":[["  2 ",{"fg":3,"bold":true}],["ecin                                                                                                                                   ",{"underline":true}]]},"cursor":{"x":6}}],[0.054788,{"lines":{"0":[["  1 ",{"fg":3}],["ech",{}],["o",{"bg":0}],[" \"this is how you should say hello\"                                                                                                ",{}]],"1":[["  2 ",{"fg":3,"bold":true}],["echin                                                                                                                                  ",{"underline":true}]]},"cursor":{"x":7}}],[0.057958,{"lines":{"0":[["  1 ",{"fg":3}],["echo",{}],[" ",{"bg":0}],["\"this is how you should say hello\"                                                                                                ",{}]],"1":[["  2 ",{"fg":3,"bold":true}],["echoin                                                                                                                                 ",{"underline":true}]]},"cursor":{"x":8}}],[0.119219,{"lines":{"0":[["  1 ",{"fg":3}],["echo ",{}],["\"",{"bg":0}],["this is how you should say hello\"                                                                                                ",{}]],"1":[["  2 ",{"fg":3,"bold":true}],["echo in                                                                                                                                ",{"underline":true}]]},"cursor":{"x":9}}],[0.512522,{"lines":{"0":[["  1 ",{"fg":3}],["echo \"",{}],["t",{"bg":0}],["his is how you should say hello\"                                                                                                ",{}]],"1":[["  2 ",{"fg":3,"bold":true}],["echo \"in                                                                                                                               ",{"underline":true}]]},"cursor":{"x":10}}],[0.005373,{"lines":{"0":[["  1 ",{"fg":3}],["echo \"t",{}],["h",{"bg":0}],["is is how you should say hello\"                                                                                                ",{}]],"1":[["  2 ",{"fg":3,"bold":true}],["echo \"\"in                                                                                                                              ",{"underline":true}]]},"cursor":{"x":11}}],[0.034095,{"lines":{"0":[["  1 ",{"fg":3}],["echo \"",{}],["t",{"bg":0}],["his is how you should say hello\"                                                                                                ",{}]],"1":[["  2 ",{"fg":3,"bold":true}],["echo \"in                                                                                                                               ",{"underline":true}]]},"cursor":{"x":10}}],[0.536492,{"lines":{"0":[["  1 ",{"fg":3}],["echo \"thi",{}],["s",{"bg":0}],[" is how you should say hello\"                                                                                                ",{}]]},"cursor":{"x":13}}],[1.064074,{"lines":{"0":[["  1 ",{"fg":3}],["echo \"this",{}],[" ",{"bg":0}],["is how you should say hello\"                                                                                                ",{}]],"1":[["  2 ",{"fg":3,"bold":true}],["echo \"in v                                                                                                                             ",{"underline":true}]]},"cursor":{"x":14}}],[0.08017100000000001,{"lines":{"0":[["  1 ",{"fg":3}],["echo \"this ",{}],["i",{"bg":0}],["s how you should say hello\"                                                                                                ",{}]],"1":[["  2 ",{"fg":3,"bold":true}],["echo \"in vi                                                                                                                            ",{"underline":true}]]},"cursor":{"x":15}}],[0.038105,{"lines":{"0":[["  1 ",{"fg":3}],["echo \"this i",{}],["s",{"bg":0}],[" how you should say hello\"                                                                                                ",{}]],"1":[["  2 ",{"fg":3,"bold":true}],["echo \"in vim                                                                                                                           ",{"underline":true}]]},"cursor":{"x":16}}],[0.601685,{"lines":{"0":[["  1 ",{"fg":3}],["echo \"this is",{}],[" ",{"bg":0}],["how you should say hello\"                                                                                                ",{}]],"1":[["  2 ",{"fg":3,"bold":true}],["echo \"in vim\"                                                                                                                          ",{"underline":true}]]},"cursor":{"x":17}}],[0.002146,{"lines":{"0":[["  1 ",{"fg":3}],["echo \"this is ",{}],["h",{"bg":0}],["ow you should say hello\"                                                                                                ",{}]],"1":[["  2 ",{"fg":3,"bold":true}],["echo \"in vim\"\"                                                                                                                         ",{"underline":true}]]},"cursor":{"x":18}}],[0.028001,{"lines":{"0":[["  1 ",{"fg":3}],["echo \"this is",{}],[" ",{"bg":0}],["how you should say hello\"                                                                                                ",{}]],"1":[["  2 ",{"fg":3,"bold":true}],["echo \"in vim\"                                                                                                                          ",{"underline":true}]]},"cursor":{"x":17}}],[0.689782,{"lines":{"0":[["  1 ",{"fg":3}],["echo \"this i",{}],["s",{"bg":0}],[" how you should say hello\"                                                                                                ",{}]],"46":[[":                                                                                                                                          ",{}]]},"cursor":{"x":1,"y":46}}],[0.247174,{"lines":{"46":[["                                                                                                                                           ",{}]]},"cursor":{"x":16,"y":1}}],[0.448523,{"lines":{"0":[["  1 ",{"fg":3,"bold":true}],["echo \"this is how you should say hello\"                                                                                                ",{"underline":true}]],"1":[["  2 ",{"fg":3}],["echo \"in vim",{}],["\"",{"bg":0}],["                                                                                                                          ",{}]],"45":[[" /tmp/bash-fc-1060478183[+]   CWD: /usr/home/patrice   Line: 1                                                                             ",{"fg":3,"bg":4,"bold":true}]]},"cursor":{"y":0}}],[0.224228,{"lines":{"1":[["  2 ",{"fg":3}],["echo \"in vim\"                           ",{}],[" ",{"bg":0}],["                                                                                              ",{}]],"46":[["-- INSERT --",{"bold":true}],["                                                                                                                               ",{}]]},"cursor":{"x":44}}],[0.223376,{"lines":{"0":[["  1 ",{"fg":3,"bold":true}],["echo \"this is how you should say hello\" ;                                                                                              ",{"underline":true}]],"1":[["  2 ",{"fg":3}],["echo \"in vim\"                            ",{}],[" ",{"bg":0}],["                                                                                             ",{}]]},"cursor":{"x":45}}],[0.70407,{"lines":{"1":[["  2 ",{"fg":3}],["echo \"in vim\"                           ",{}],[" ",{"bg":0}],["                                                                                              ",{}]],"46":[["                                                                                                                                dl         ",{}]]},"cursor":{"x":44,"visible":false}}],[0.023359,{"lines":{"0":[["  1 ",{"fg":3,"bold":true}],["echo \"this is how you should say hello\"                                                                                                ",{"underline":true}]],"1":[["  2 ",{"fg":3}],["echo \"in vim\"                          ",{}],[" ",{"bg":0}],["                                                                                               ",{}]],"46":[["                                                                                                                                           ",{}]]},"cursor":{"x":43,"visible":true}}],[0.105881,{"lines":{"1":[["  2 ",{"fg":3}],["echo \"in vim\"                         ",{}],[" ",{"bg":0}],["                                                                                                ",{}]]},"cursor":{"x":42}}],[0.375274,{"lines":{"1":[["  2 ",{"fg":3}],["echo \"in vim\"                          ",{}],[" ",{"bg":0}],["                                                                                               ",{}]],"46":[["-- INSERT --",{"bold":true}],["                                                                                                                               ",{}]]},"cursor":{"x":43}}],[0.303323,{"lines":{"0":[["  1 ",{"fg":3,"bold":true}],["echo \"this is how you should say hello\";                                                                                               ",{"underline":true}]],"1":[["  2 ",{"fg":3}],["echo \"in vim\"                           ",{}],[" ",{"bg":0}],["                                                                                              ",{}]]},"cursor":{"x":44}}],[0.440539,{"lines":{"1":[["  2 ",{"fg":3}],["echo \"in vim\"                          ",{}],[" ",{"bg":0}],["                                                                                               ",{}]],"46":[[":                                                                                                                                          ",{}]]},"cursor":{"x":1,"y":46}}],[0.110727,{"lines":{"46":[[":w                                                                                                                                         ",{}]]},"cursor":{"x":2}}],[0.08827699999999999,{"lines":{"46":[[":wq                                                                                                                                        ",{}]]},"cursor":{"x":3}}],[0.088661,{"cursor":{"x":0,"visible":false}}],[0.012859,{"lines":{"46":[["\"/tmp/bash-fc-1060478183\"                                                                                                                  ",{}]]},"cursor":{"x":25}}],[0.009835,{"lines":{"0":[["patrice@lair",{"fg":2,"bold":true}],[" ~ $",{"fg":4,"bold":true}],[" this is how you should say hello                                                                                          ",{}]],"1":[["echo \"this is how you should say hello\";                                                                                                   ",{}]],"2":[["this is how you should say hello                                                                                                           ",{}]],"3":[["echo \"in vim\"                                                                                                                              ",{}]],"4":[["in vim                                                                                                                                     ",{}]],"5":[["patrice@lair",{"fg":2,"bold":true}],[" ~ $",{"fg":4,"bold":true}],["                                                                                                                           ",{}]],"6":[["                                                                                                                                           ",{}]],"7":[["                                                                                                                                           ",{}]],"8":[["                                                                                                                                           ",{}]],"9":[["                                                                                                                                           ",{}]],"10":[["                                                                                                                                           ",{}]],"11":[["                                                                                                                                           ",{}]],"12":[["                                                                                                                                           ",{}]],"13":[["                                                                                                                                           ",{}]],"14":[["                                                                                                                                           ",{}]],"15":[["                                                                                                                                           ",{}]],"16":[["                                                                                                                                           ",{}]],"17":[["                                                                                                                                           ",{}]],"18":[["                                                                                                                                           ",{}]],"19":[["                                                                                                                                           ",{}]],"20":[["                                                                                                                                           ",{}]],"21":[["                                                                                                                                           ",{}]],"22":[["                                                                                                                                           ",{}]],"23":[["                                                                                                                                           ",{}]],"24":[["                                                                                                                                           ",{}]],"25":[["                                                                                                                                           ",{}]],"26":[["                                                                                                                                           ",{}]],"27":[["                                                                                                                                           ",{}]],"28":[["                                                                                                                                           ",{}]],"29":[["                                                                                                                                           ",{}]],"30":[["                                                                                                                                           ",{}]],"31":[["                                                                                                                                           ",{}]],"32":[["                                                                                                                                           ",{}]],"33":[["                                                                                                                                           ",{}]],"34":[["                                                                                                                                           ",{}]],"35":[["                                                                                                                                           ",{}]],"36":[["                                                                                                                                           ",{}]],"37":[["                                                                                                                                           ",{}]],"38":[["                                                                                                                                           ",{}]],"39":[["                                                                                                                                           ",{}]],"40":[["                                                                                                                                           ",{}]],"41":[["                                                                                                                                           ",{}]],"42":[["                                                                                                                                           ",{}]],"43":[["                                                                                                                                           ",{}]],"44":[["                                                                                                                                           ",{}]],"45":[["                                                                                                                                           ",{}]],"46":[["                                                                                                                                           ",{}]]},"cursor":{"x":17,"y":5,"visible":true}}],[5.039475,{"lines":{"5":[["patrice@lair",{"fg":2,"bold":true}],[" ~ $",{"fg":4,"bold":true}],[" B                                                                                                                         ",{}]]},"cursor":{"x":18}}],[0.175937,{"lines":{"5":[["patrice@lair",{"fg":2,"bold":true}],[" ~ $",{"fg":4,"bold":true}],[" BI                                                                                                                        ",{}]]},"cursor":{"x":19}}],[0.2492,{"lines":{"5":[["patrice@lair",{"fg":2,"bold":true}],[" ~ $",{"fg":4,"bold":true}],[" BIM                                                                                                                       ",{}]]},"cursor":{"x":20}}],[0.207707,{"lines":{"5":[["patrice@lair",{"fg":2,"bold":true}],[" ~ $",{"fg":4,"bold":true}],[" BIM!                                                                                                                      ",{}]]},"cursor":{"x":21}}],[0.576353,{"cursor":{"x":17}}],[0.391809,{"lines":{"5":[["patrice@lair",{"fg":2,"bold":true}],[" ~ $",{"fg":4,"bold":true}],["                                                                                                                           ",{}]]}}],[1.504843,{"lines":{"5":[["patrice@lair",{"fg":2,"bold":true}],[" ~ $",{"fg":4,"bold":true}],[" exit                                                                                                                      ",{}]]},"cursor":{"x":0,"y":6}}]]